pyweld-0.0.6.dist-info/DESCRIPTION.rst
pyweld-0.0.6.dist-info/METADATA
pyweld-0.0.6.dist-info/RECORD
pyweld-0.0.6.dist-info/WHEEL
pyweld-0.0.6.dist-info/metadata.json
pyweld-0.0.6.dist-info/top_level.txt
weld/__init__.py
weld/bindings.py
weld/encoders.py
weld/libweld.dylib
weld/types.py
weld/weldobject.py
