Metadata-Version: 2.0
Name: pyweld
Version: 0.0.6
Summary: UNKNOWN
Home-page: https://github.com/weld-project/weld
Author: Weld Developers
Author-email: weld-group@lists.stanford.edu
License: UNKNOWN
Platform: UNKNOWN
Requires-Dist: pandas
Requires-Dist: numpy
